duckdb-stubs/__init__.pyi
duckdb-stubs/value/__init__.pyi
duckdb-stubs/value/constant/__init__.pyi
duckdb-stubs/typing/__init__.pyi
duckdb-stubs/functional/__init__.pyi
smokedduck/filesystem.py
smokedduck/__init__.py
smokedduck/bytes_io_wrapper.py
smokedduck/udf.py
smokedduck/duckdb.cpython-311-darwin.so
smokedduck/experimental/__init__.py
smokedduck/experimental/spark/exception.py
smokedduck/experimental/spark/_typing.py
smokedduck/experimental/spark/LICENSE
smokedduck/experimental/spark/_globals.py
smokedduck/experimental/spark/conf.py
smokedduck/experimental/spark/__init__.py
smokedduck/experimental/spark/context.py
smokedduck/experimental/spark/errors/error_classes.py
smokedduck/experimental/spark/errors/__init__.py
smokedduck/experimental/spark/errors/utils.py
smokedduck/experimental/spark/errors/exceptions/__init__.py
smokedduck/experimental/spark/errors/exceptions/base.py
smokedduck/experimental/spark/sql/catalog.py
smokedduck/experimental/spark/sql/functions.py
smokedduck/experimental/spark/sql/_typing.py
smokedduck/experimental/spark/sql/dataframe.py
smokedduck/experimental/spark/sql/conf.py
smokedduck/experimental/spark/sql/session.py
smokedduck/experimental/spark/sql/type_utils.py
smokedduck/experimental/spark/sql/__init__.py
smokedduck/experimental/spark/sql/types.py
smokedduck/experimental/spark/sql/readwriter.py
smokedduck/experimental/spark/sql/group.py
smokedduck/experimental/spark/sql/udf.py
smokedduck/experimental/spark/sql/streaming.py
smokedduck/experimental/spark/sql/column.py
smokedduck/query_graph/__main__.py
smokedduck/value/constant.py
smokedduck/typing/__init__.py
smokedduck/provenance/smokedduck.py
smokedduck/provenance/sql_statements.py
smokedduck/provenance/provenance_models.py
smokedduck/provenance/operators.py
smokedduck/provenance/lineage_query.py
smokedduck/functional/__init__.py
smokedduck-0.1.dev36241.dist-info/RECORD
smokedduck-0.1.dev36241.dist-info/WHEEL
smokedduck-0.1.dev36241.dist-info/top_level.txt
smokedduck-0.1.dev36241.dist-info/METADATA
adbc_driver_duckdb/dbapi.py
adbc_driver_duckdb/__init__.py
