Metadata-Version: 2.1
Name: smokedduck
Version: 0.1.dev36241
Summary: SmokedDuck - DuckDB fork with fine-grained provenance
Maintainer: Haneen Mohammed
Maintainer-email: ham2156@columbia.edu
License: MIT
Keywords: SmokedDuck DuckDB Database SQL OLAP Provenance
Classifier: Topic :: Database :: Database Engines/Servers
Classifier: Intended Audience :: Developers
Classifier: License :: OSI Approved :: MIT License
Requires-Python: >=3.7.0
